[
 {
   "committee_type": "Anti-Ragging Committee",
   "order_reference": "BIMT/027(O)/24-25",
   "appointment_date": "08.07.2024",
   "member_name": "Prof S.S.Huda",
   "designation": "CHAIRMAN"
 },
 {
   "committee_type": "Anti-Ragging Committee",
   "order_reference": "BIMT/027(O)/24-25",
   "appointment_date": "08.07.2024",
   "member_name": "Pranoy Chattoraj",
   "designation": "MEMBER"
 },
 {
   "committee_type": "Anti-Ragging Committee",
   "order_reference": "BIMT/027(O)/24-25",
   "appointment_date": "08.07.2024",
   "member_name": "Kazi Imran Ahmed",
   "designation": "MEMBER"
 },
 {
   "committee_type": "Anti-Ragging Committee",
   "order_reference": "BIMT/027(O)/24-25",
   "appointment_date": "08.07.2024",
   "member_name": "Dinonath Mishra",
   "designation": "MEMBER"
 },
 {
   "committee_type": "Anti-Ragging Committee",
   "order_reference": "BIMT/027(O)/24-25",
   "appointment_date": "08.07.2024",
   "member_name": "Rakhi Saha",
   "designation": "MEMBER"
 },
 {
   "committee_type": "Anti-Ragging Committee",
   "order_reference": "BIMT/027(O)/24-25",
   "appointment_date": "08.07.2024",
   "member_name": "Samprity Chowdhury",
   "designation": "MEMBER"
 },
 {
   "committee_type": "Anti-Ragging Committee",
   "order_reference": "BIMT/027(O)/24-25",
   "appointment_date": "08.07.2024",
   "member_name": "Officer-In-Charge, PS-Nabagram,Murshidanad",
   "designation": "MEMBER"
 },
 {
   "committee_type": "Anti-Ragging Squad",
   "order_reference": "BIMT/027(O)/24-25",
   "appointment_date": "08.07.2024",
   "member_name": "Sanchita Sarkar",
   "designation": "MEMBER"
 },
 {
   "committee_type": "Anti-Ragging Squad",
   "order_reference": "BIMT/027(O)/24-25",
   "appointment_date": "08.07.2024",
   "member_name": "Sumit Nath",
   "designation": "MEMBER"
 },
 {
   "committee_type": "Anti-Ragging Squad",
   "order_reference": "BIMT/027(O)/24-25",
   "appointment_date": "08.07.2024",
   "member_name": "Prabir Mandal",
   "designation": "MEMBER"
 },
 {
   "committee_type": "Anti-Ragging Squad",
   "order_reference": "BIMT/027(O)/24-25",
   "appointment_date": "08.07.2024",
   "member_name": "Kaushik Mandal",
   "designation": "MEMBER"
 }
]